datalad_xnat/__init__.py
datalad_xnat/_version.py
datalad_xnat/conftest.py
datalad_xnat/init.py
datalad_xnat/parser.py
datalad_xnat/platform.py
datalad_xnat/query_files.py
datalad_xnat/update.py
datalad_xnat/resources/procedures/cfg_xnat_dataset.py
datalad_xnat/tests/__init__.py
datalad_xnat/tests/test_init.py
datalad_xnat/tests/test_nitrcir.py
datalad_xnat/tests/test_register.py
datalad_xnat/tests/test_update.py
datalad_xnat/tests/test_xnatcentral.py
datalad_xnat-0.2.1.dist-info/LICENSE
datalad_xnat-0.2.1.dist-info/METADATA
datalad_xnat-0.2.1.dist-info/WHEEL
datalad_xnat-0.2.1.dist-info/entry_points.txt
datalad_xnat-0.2.1.dist-info/top_level.txt
datalad_xnat-0.2.1.dist-info/RECORD
