Metadata-Version: 2.1
Name: datalad-xnat
Version: 0.2.1
Summary: DataLad support for XNAT server access
Home-page: https://github.com/datalad/datalad-xnat
Author: Michael Hanke
Author-email: michael.hanke@gmail.com
License: MIT
Classifier: Programming Language :: Python
Classifier: License :: OSI Approved :: MIT License
Classifier: Programming Language :: Python :: 3
Requires-Python: >=3.8
License-File: LICENSE
Requires-Dist: datalad (>=0.18.0)
Requires-Dist: requests
Provides-Extra: devel
Requires-Dist: coverage ; extra == 'devel'
Requires-Dist: pytest ; extra == 'devel'
Requires-Dist: pytest-cov ; extra == 'devel'
Provides-Extra: devel-utils
Requires-Dist: pytest-xdist ; extra == 'devel-utils'
Requires-Dist: scriv ; extra == 'devel-utils'
